mtrx/__init__.py
mtrx/mtrx.py
mtrx-0.1.5.dist-info/LICENSE
mtrx-0.1.5.dist-info/METADATA
mtrx-0.1.5.dist-info/WHEEL
mtrx-0.1.5.dist-info/top_level.txt
mtrx-0.1.5.dist-info/RECORD
