Metadata-Version: 2.1
Name: mtrx
Version: 0.1.5
Summary: A Python ToolBox
Home-page: https://mtrx.ir
Author: Mostafa Vahedi Nejad
Author-email: mostafa.vahedi.nejad@gmail.com
License: MIT
Download-URL: https://github.com/mostafa-vn/mtrx.git
Keywords: mtrx mostafa matrix python v3
Platform: any
Classifier: Programming Language :: Python :: 3
Classifier: License :: OSI Approved :: MIT License
Classifier: Operating System :: OS Independent
Classifier: Development Status :: 4 - Beta
Classifier: Intended Audience :: Developers
Classifier: Environment :: Console
Classifier: Topic :: Software Development :: Libraries :: Python Modules
Requires-Dist: requests
Requires-Dist: pyqrcode
Requires-Dist: dnspython
Requires-Dist: autopy
